[ 
        {
            "name" : "html header",
            "id" : 14,
            "highlights" : [ 
                {
                    "select_type" : "html",
                    "begin_line" : "0",
                    "begin_ch" : "0",
                    "end_line" : "2",
                    "end_ch" : "4",
                    "selection" : "Clock Box v3\n<br>\n<br>",
                    "hid" : 2
                }
            ],
            "highlightID" : 2,
            "universal_name" : "design_parts",
            "universal_description" : "this text is added to make the output look nice and is not covered in the lesson",
            "questions" : [ 
                "QQ-30434"
            ]
        }, 
        {
            "name" : "html fotter",
            "id" : 15,
            "highlights" : [ 
                {
                    "select_type" : "html",
                    "begin_line" : "4",
                    "begin_ch" : "0",
                    "end_line" : "5",
                    "end_ch" : "15",
                    "selection" : "<hr>\n<br> Thu 16 Nov",
                    "hid" : 2
                }
            ],
            "highlightID" : 2,
            "universal_name" : "design_parts",
            "questions" : [ 
                "QQ-30434"
            ],
            "universal_description" : "this text is added to make the output look nice and is not covered in the lesson"
        }, 
        {
            "name" : "create an empty Span",
            "id" : 3,
            "highlights" : [ 
                {
                    "select_type" : "html",
                    "begin_line" : "3",
                    "begin_ch" : "0",
                    "end_line" : "3",
                    "end_ch" : "5",
                    "selection" : "<span",
                    "hid" : 8
                }, 
                {
                    "select_type" : "html",
                    "begin_line" : "3",
                    "begin_ch" : "39",
                    "end_line" : "3",
                    "end_ch" : "40",
                    "selection" : ">",
                    "hid" : 9
                }, 
                {
                    "select_type" : "html",
                    "begin_line" : "3",
                    "begin_ch" : "45",
                    "end_line" : "3",
                    "end_ch" : "52",
                    "selection" : "</span>",
                    "hid" : 10
                }
            ],
            "highlightID" : 12,
            "universal_name" : "empty span",
            "universal_description" : "a Span is used when you want to give some text a visible attribute",
            "questions" : [ 
                "QQ-9115227", 
                "QQ-6110031"
            ]
        }, 
        {
            "name" : "add an id to a html element",
            "id" : 2,
            "highlights" : [ 
                {
                    "select_type" : "html",
                    "begin_line" : "3",
                    "begin_ch" : "6",
                    "end_line" : "3",
                    "end_ch" : "8",
                    "selection" : "id",
                    "hid" : 13
                }, 
                {
                    "select_type" : "html",
                    "begin_line" : "3",
                    "begin_ch" : "8",
                    "end_line" : "3",
                    "end_ch" : "9",
                    "selection" : "=",
                    "hid" : 15
                }, 
                {
                    "select_type" : "html",
                    "begin_line" : "3",
                    "begin_ch" : "9",
                    "end_line" : "3",
                    "end_ch" : "10",
                    "selection" : "\"",
                    "hid" : 16
                }, 
                {
                    "select_type" : "html",
                    "begin_line" : "3",
                    "begin_ch" : "19",
                    "end_line" : "3",
                    "end_ch" : "20",
                    "selection" : "\"",
                    "hid" : 17
                }, 
                {
                    "select_type" : "html",
                    "begin_line" : "3",
                    "begin_ch" : "10",
                    "end_line" : "3",
                    "end_ch" : "19",
                    "selection" : "_HTML_num",
                    "hid" : 18
                }
            ],
            "highlightID" : 18,
            "universal_name" : "add id",
            "questions" : [ 
                "QQ-8858012"
            ]
        }, 
        {
            "name" : "add a class to an html element",
            "id" : 8,
            "highlights" : [ 
                {
                    "select_type" : "html",
                    "begin_line" : "3",
                    "begin_ch" : "21",
                    "end_line" : "3",
                    "end_ch" : "26",
                    "selection" : "class",
                    "hid" : 7
                }, 
                {
                    "select_type" : "html",
                    "begin_line" : "3",
                    "begin_ch" : "26",
                    "end_line" : "3",
                    "end_ch" : "27",
                    "selection" : "=",
                    "hid" : 8
                }, 
                {
                    "select_type" : "html",
                    "begin_line" : "3",
                    "begin_ch" : "27",
                    "end_line" : "3",
                    "end_ch" : "28",
                    "selection" : "\"",
                    "hid" : 9
                }, 
                {
                    "select_type" : "html",
                    "begin_line" : "3",
                    "begin_ch" : "38",
                    "end_line" : "3",
                    "end_ch" : "39",
                    "selection" : "\"",
                    "hid" : 10
                }, 
                {
                    "select_type" : "html",
                    "begin_line" : "3",
                    "begin_ch" : "28",
                    "end_line" : "3",
                    "end_ch" : "38",
                    "selection" : "_CSS_clock",
                    "hid" : 11
                }
            ],
            "highlightID" : 11,
            "universal_name" : "add class",
            "questions" : [ 
                "QQ-920623", 
                "QQ-6110031"
            ]
        }, 
        {
            "name" : "add text into an html element",
            "id" : 4,
            "highlights" : [ 
                {
                    "select_type" : "html",
                    "begin_line" : "3",
                    "begin_ch" : "40",
                    "end_line" : "3",
                    "end_ch" : "45",
                    "selection" : "00000",
                    "hid" : 4
                }
            ],
            "highlightID" : 4,
            "universal_name" : "add text"
        }
]